Workbook

Sheet Executive Summary
A1: Financial Model - E-commerce Market Entry
A3: Key Metrics Dashboard
A5: Total Investment Required: | B5: ='Investment Requirements'!B10 -> 0
A6: 3-Year Revenue Projection: | B6: ='Revenue Model'!B20 -> 0
A7: Breakeven Month: | B7: ='Profit & Loss'!B25 -> 0
A8: ROI (3-Year): | B8: ='Profit & Loss'!B30 -> 0
A9: Payback Period: | B9: ='Investment Requirements'!B15 -> 207000

Sheet Revenue Model
A1: Revenue Projections
A3: Year 1 | B3: Year 2 | C3: Year 3
A5: Customers
A6: New Customers | B6: 25000 | C6: =B6*1.8 -> 45000 | D6: =C6*1.6 -> 72000
A7: Total Customers | B7: =B6 -> 25000 | C7: =B7+C6 -> 70000 | D7: =C7+D6 -> 142000
A9: Sales Metrics
A10: Average Order Value | B10: 85 | C10: =B10*1.08 -> 91.8 | D10: =C10*1.06 -> 97.308
A11: Orders per Customer | B11: 1.2 | C11: 1.4 | D11: 1.6
A12: Monthly Revenue | B12: =B7*B10*B11/12 -> 212500
A14: Revenue by Channel
A15: Marketplace | B15: 0.7 | C15: 0.6 | D15: 0.5
A16: D2C Website | B16: 0.3 | C16: 0.4 | D16: 0.5

Sheet Cost Structure
A1: Cost Structure
A3: Variable Costs (% of Revenue)
A5: Cost of Goods Sold | B5: 0.45 | C5: 0.43 | D5: 0.42
A6: Payment Processing | B6: 0.025 | C6: 0.025 | D6: 0.025
A7: Shipping & Handling | B7: 0.08 | C7: 0.07 | D7: 0.06
A8: Returns & Refunds | B8: 0.05 | C8: 0.04 | D8: 0.03
A10: Fixed Costs (Monthly)
A11: Team Salaries | B11: 15000 | C11: 18000 | D11: 20000
A12: Marketing Retainer | B12: 10000 | C12: 12000 | D12: 15000
A13: Software Subscriptions | B13: 2000 | C13: 2500 | D13: 3000
A14: Office & Operations | B14: 3000 | C14: 3500 | D14: 4000

Sheet Investment Requirements
A1: Investment Requirements
A3: One-Time Costs
A5: Technology Setup | B5: 50000
A6: Legal & Incorporation | B6: 15000
A7: Initial Inventory | B7: 75000
A8: Market Research | B8: 10000
A9: Total One-Time | B9: =SUM(B5:B8) -> 150000
A11: Working Capital (3 Months)
A12: Operating Expenses | B12: ='Cost Structure'!B15*3 -> 0
A13: Marketing Buffer | B13: 30000
A14: Contingency (15%) | B14: =(B9+B12+B13)*0.15 -> 27000
A15: Total Investment | B15: =SUM(B9:B14) -> 207000

Sheet Profit & Loss
A1: Profit & Loss Statement
A3: Year 1 | B3: Year 2 | C3: Year 3
A5: Revenue
A6: Total Revenue | B6: ='Revenue Model'!B12*12 -> 2550000
A8: Cost of Sales
A9: COGS | B9: =B6*'Cost Structure'!B5 -> 1147500
A10: Gross Profit | B10: =B6-B9 -> 1402500
A11: Gross Margin % | B11: =B10/B6 -> 0.55
A13: Operating Expenses
A14: Team Costs | B14: ='Cost Structure'!B11*12 -> 180000
A15: Marketing | B15: ='Cost Structure'!B12*12 -> 120000
A16: Software | B16: ='Cost Structure'!B13*12 -> 24000
A17: Operations | B17: ='Cost Structure'!B14*12 -> 36000
A18: Total OpEx | B18: =SUM(B14:B17) -> 360000
A20: EBITDA
A21: EBITDA | B21: =B10-B18 -> 1042500
A22: EBITDA Margin % | B22: =B21/B6 -> 0.40882353

Sheet Cash Flow
A1: Monthly Cash Flow
A3: Month | B3: 1 | C3: 2 | D3: 3 | E3: 4 | F3: 5 | G3: 6 | H3: 7 | I3: 8 | J3: 9 | K3: 10 | L3: 11 | M3: 12 | N3: 13 | O3: 14 | P3: 15 | Q3: 16 | R3: 17 | S3: 18 | T3: 19 | U3: 20 | V3: 21 | W3: 22 | X3: 23 | Y3: 24 | Z3: 25 | AA3: 26 | AB3: 27 | AC3: 28 | AD3: 29 | AE3: 30 | AF3: 31 | AG3: 32 | AH3: 33 | AI3: 34 | AJ3: 35 | AK3: 36
A5: Cash In
A6: Revenue | B6: ='Revenue Model'!B12 -> 212500
A8: Cash Out
A9: COGS | B9: =B6*'Cost Structure'!B5 -> 95625
A10: Fixed Costs | B10: =SUM('Cost Structure'!B11:B14) -> 30000
A11: Marketing Variable | B11: =B6*0.15 -> 31875
A13: Net Cash Flow | B13: =B6-SUM(B9:B11) -> 55000
A14: Cumulative Cash | B14: ='Investment Requirements'!B15+B13 -> 262000

Sheet KPIs & Metrics
A1: Key Performance Indicators
A3: Customer Metrics
A5: CAC (Customer Acquisition Cost) | B5: ='Cost Structure'!B12/'Revenue Model'!B6 -> 0.4
A6: LTV (Lifetime Value) | B6: ='Revenue Model'!B10*'Revenue Model'!B11*12 -> 1224
A7: LTV/CAC Ratio | B7: =B6/B5 -> 3060
A9: Financial Metrics
A10: Gross Margin | B10: ='Profit & Loss'!B11 -> 0.55
A11: Operating Margin | B11: ='Profit & Loss'!B22 -> 0.40882353
A12: Monthly Burn Rate | B12: ='Cash Flow'!B10 -> 30000
A13: Runway (Months) | B13: ='Investment Requirements'!B15/B12 -> 6.9

Sheet Sensitivity Analysis
A1: Sensitivity Analysis - Impact on Year 3 Revenue
A3: Scenario | B3: Base Case | C3: Optimistic | D3: Pessimistic
A5: Assumptions
A6: Customer Growth | B6: 0.6 | C6: 0.8 | D6: 0.4
A7: Average Order Value | B7: 0.06 | C7: 0.1 | D7: 0.02
A8: Conversion Rate | B8: 0.028 | C8: 0.035 | D8: 0.02
A10: Results
A11: Year 3 Revenue | B11: ='Revenue Model'!D12*12 -> 0
A12: Year 3 EBITDA | B12: ='Profit & Loss'!C21 -> 0
